.gitignore
HISTORY.rst
LICENSE
MANIFEST.in
README.rst
setup.py
daemonocle/__init__.py
daemonocle/cli.py
daemonocle/daemon.py
daemonocle/exceptions.py
xdaemonocle.egg-info/PKG-INFO
xdaemonocle.egg-info/SOURCES.txt
xdaemonocle.egg-info/dependency_links.txt
xdaemonocle.egg-info/requires.txt
xdaemonocle.egg-info/top_level.txt