Metadata-Version: 1.1
Name: xdaemonocle
Version: 0.8.1
Summary: A Python library for creating super fancy Unix daemons
Home-page: http://github.com/jnrbsn/daemonocle
Author: Jonathan Robson
Author-email: jnrbsn@gmail.com
License: MIT
Keywords: daemon daemonize fork unix cli
Platform: UNKNOWN
Classifier: Development Status :: 4 - Beta
Classifier: Intended Audience :: Developers
Classifier: Intended Audience :: System Administrators
Classifier: License :: OSI Approved :: MIT License
Classifier: Operating System :: MacOS :: MacOS X
Classifier: Operating System :: POSIX :: Linux
Classifier: Programming Language :: Python :: 2
Classifier: Programming Language :: Python :: 2.7
